LICENSE
MANIFEST.in
README.md
setup.py
bin/semanticversion
semanticversion/__init__.py
semanticversion/main.py
semanticversion/version.py
semanticversion.egg-info/PKG-INFO
semanticversion.egg-info/SOURCES.txt
semanticversion.egg-info/dependency_links.txt
semanticversion.egg-info/top_level.txt