Metadata-Version: 1.0
Name: semanticversion
Version: 0.1.7
Summary: Version generator tool. Semver, markdown json woohoo!
Home-page: https://github.com/oskarnyqvist/semanticversion
Author: oskarnyqvist
Author-email: oskarnyqvist@gmail.com
License: The MIT License (MIT)
